feroxbuster_cli/__init__.py
feroxbuster_cli/cli.py
feroxbuster_cli-0.1.7.dist-info/METADATA
feroxbuster_cli-0.1.7.dist-info/WHEEL
feroxbuster_cli-0.1.7.dist-info/entry_points.txt
feroxbuster_cli-0.1.7.dist-info/top_level.txt
feroxbuster_cli-0.1.7.dist-info/RECORD
