Metadata-Version: 2.1
Name: feroxbuster-cli
Version: 0.1.7
Summary: A Python CLI tool to download and run Feroxbuster
Author: Adithya A N
Classifier: Programming Language :: Python :: 3
Classifier: License :: OSI Approved :: MIT License
Classifier: Operating System :: OS Independent
Requires-Python: >=3.6
Requires-Dist: requests
